{"Jeremy Shaw": {"extended_title": "Jeremy Shaw the bastard, Baron of the King's sock drawer", "full_title": "Baron of the King's sock drawer", "happiness": 5, "relations": {"Rowan \"The rock\" Mcgruffy": 8, "Megan Sonson": 1, "Hannah Jogioja": 4, "Sam Jogioja": 6, "Gavin Windsor": 8}, "full_name": "Jeremy Shaw", "marked_for_death": false, "death_message": "I shouldn't be dead!", "nobility": 10, "surname": "Shaw", "gender": "m", "honour": 3, "id": 103, "ram_status": null, "wealth": 7862}, "Rowan \"The rock\" Mcgruffy": {"extended_title": "Rowan \"The rock\" Mcgruffy the bastard, Marquis of Devon", "full_title": "Marquis of Devon", "happiness": 6, "relations": {"Jeremy Shaw": 7, "Megan Sonson": 6, "Hannah Jogioja": 10, "Sam Jogioja": 4, "Gavin Windsor": 4}, "full_name": "Rowan \"The rock\" Mcgruffy", "marked_for_death": false, "death_message": "I shouldn't be dead!", "nobility": 9, "surname": "\"The rock\" Mcgruffy", "gender": "m", "honour": 3, "id": 104, "ram_status": null, "wealth": 7862}, "Megan Sonson": {"extended_title": "Megan Sonson the impotent, Lady of the shitty part of Amsterdam", "full_title": "Lady of the shitty part of Amsterdam", "happiness": 5, "relations": {"Jeremy Shaw": 9, "Rowan \"The rock\" Mcgruffy": 4, "Hannah Jogioja": 6, "Sam Jogioja": 3, "Gavin Windsor": 6}, "full_name": "Megan Sonson", "marked_for_death": false, "death_message": "I shouldn't be dead!", "nobility": 6, "surname": "Sonson", "gender": "f", "honour": 8, "id": 105, "ram_status": null, "wealth": 3259}, "Hannah Jogioja": {"extended_title": "Hannah Jogioja, Inventor of the Whirligig Thingmabob", "full_title": null, "happiness": 9, "relations": {"Jeremy Shaw": 7, "Rowan \"The rock\" Mcgruffy": 3, "Megan Sonson": 2, "Sam Jogioja": 10, "Gavin Windsor": 3}, "full_name": "Hannah Jogioja", "marked_for_death": false, "death_message": "I shouldn't be dead!", "nobility": 1, "surname": "Jogioja", "gender": "f", "honour": 10, "id": 100, "ram_status": null, "wealth": 4357}, "Sam Jogioja": {"extended_title": "Sam Jogioja the drunk, Earl of London", "full_title": "Earl of London", "happiness": 6, "relations": {"Jeremy Shaw": 9, "Rowan \"The rock\" Mcgruffy": 9, "Megan Sonson": 6, "Hannah Jogioja": 9, "Gavin Windsor": 1}, "full_name": "Sam Jogioja", "marked_for_death": false, "death_message": "I shouldn't be dead!", "nobility": 9, "surname": "Jogioja", "gender": "m", "honour": 10, "id": 101, "ram_status": null, "wealth": 3485}, "Gavin Windsor": {"extended_title": "Gavin Windsor the inexplicable, Duke of SCIENCE", "full_title": "Duke of SCIENCE", "happiness": 7, "relations": {"Jeremy Shaw": 2, "Rowan \"The rock\" Mcgruffy": 10, "Megan Sonson": 6, "Hannah Jogioja": 10, "Sam Jogioja": 5}, "full_name": "Gavin Windsor", "marked_for_death": false, "death_message": "I shouldn't be dead!", "nobility": 6, "surname": "Windsor", "gender": "m", "honour": 10, "id": 102, "ram_status": null, "wealth": 3485}}